<?xml version="1.0" encoding="UTF-8"?><record_update>
    <sys_choice action="DELETE" field="u_what_needed" table="x_58872_needit_needit" version="3">
        <sys_choice_set action="DELETE">
            <element>u_what_needed</element>
            <name>x_58872_needit_needit</name>
            <sys_class_name/>
            <sys_created_by/>
            <sys_created_on/>
            <sys_id/>
            <sys_mod_count/>
            <sys_name/>
            <sys_package/>
            <sys_policy/>
            <sys_scope/>
            <sys_update_name/>
            <sys_updated_by/>
            <sys_updated_on>2020-07-06 16:57:29</sys_updated_on>
        </sys_choice_set>
    </sys_choice>
    <sys_update_version action="INSERT_OR_UPDATE">
        <action>DELETE</action>
        <application/>
        <file_path/>
        <instance_id>1274646fdbf31b046578f22ebf961948</instance_id>
        <instance_name>dev70300</instance_name>
        <name>sys_choice_x_58872_needit_needit_u_what_needed</name>
        <payload><![CDATA[<?xml version="1.0" encoding="UTF-8"?><record_update><sys_choice action="DELETE" field="u_what_needed" table="x_58872_needit_needit" version="3"><sys_choice_set action="DELETE"><element>u_what_needed</element><name>x_58872_needit_needit</name><sys_class_name/><sys_created_by/><sys_created_on/><sys_id/><sys_mod_count/><sys_name/><sys_package/><sys_policy/><sys_scope/><sys_update_name/><sys_updated_by/><sys_updated_on>2020-07-06 16:57:29</sys_updated_on></sys_choice_set></sys_choice></record_update>]]></payload>
        <payload_hash>-429457270</payload_hash>
        <record_name>x_58872_needit_needit.u_what_needed</record_name>
        <reverted_from/>
        <source>5dd87a11dbb91010dadaab7dca96196c</source>
        <source_table>sys_update_set</source_table>
        <state>previous</state>
        <sys_created_by>admin</sys_created_by>
        <sys_created_on>2020-07-06 16:57:29</sys_created_on>
        <sys_id>c00c4a1adb311010dadaab7dca9619d3</sys_id>
        <sys_mod_count>0</sys_mod_count>
        <sys_recorded_at>173250fa5360000001</sys_recorded_at>
        <sys_updated_by>admin</sys_updated_by>
        <sys_updated_on>2020-07-06 16:57:29</sys_updated_on>
        <type>Choice list</type>
        <update_guid>4c0c4a1add31101045f0678bc3c466d2</update_guid>
        <update_guid_history>4c0c4a1add31101045f0678bc3c466d2:-429457270,080c4a1aa2311010ed1858c7288a37cf:-914036937,840c4a1a50311010a29972cbeec510cc:-760451526,040c4a1a8731101032b4a452201386c9:266010744,800c4a1a7d311010fd305afd92bc99c6:1477413627,33fb4a1a753110103076bafe7b8a98c3:51121421,bffb4a1a9c3110109ad4bb36d18e20bf:-1207116168,3ffb4a1a0d3110106c931e79399df7bc:1855535508,e22157112df910101513ce6403904568:-1462851373</update_guid_history>
    </sys_update_version>
    <sys_metadata_delete action="INSERT_OR_UPDATE">
        <sys_audit_delete/>
        <sys_class_name>sys_metadata_delete</sys_class_name>
        <sys_created_by>admin</sys_created_by>
        <sys_created_on>2020-07-06 16:57:38</sys_created_on>
        <sys_db_object display_value="" name="sys_choice_set">sys_choice_set</sys_db_object>
        <sys_id>f10cca1adb311010dadaab7dca961995</sys_id>
        <sys_metadata>f10cca1adb311010dadaab7dca961995</sys_metadata>
        <sys_mod_count>0</sys_mod_count>
        <sys_name>u_what_needed</sys_name>
        <sys_package display_value="NeedIt" source="x_58872_needit">6ead8e780f603200cd674f8ce1050ed1</sys_package>
        <sys_parent/>
        <sys_policy/>
        <sys_scope display_value="NeedIt">6ead8e780f603200cd674f8ce1050ed1</sys_scope>
        <sys_scope_delete display_value="">94872a8897db403e8ee69a431de2fca4</sys_scope_delete>
        <sys_update_name>sys_choice_x_58872_needit_needit_u_what_needed</sys_update_name>
        <sys_update_version display_value="sys_choice_x_58872_needit_needit_u_what_needed">c00c4a1adb311010dadaab7dca9619d3</sys_update_version>
        <sys_updated_by>admin</sys_updated_by>
        <sys_updated_on>2020-07-06 16:57:38</sys_updated_on>
    </sys_metadata_delete>
</record_update>
